example_package_iker8/__init__.py
example_package_iker8/example.py
example_package_iker8-0.0.1.dist-info/METADATA
example_package_iker8-0.0.1.dist-info/WHEEL
example_package_iker8-0.0.1.dist-info/licenses/LICENSE
example_package_iker8-0.0.1.dist-info/RECORD
