Metadata-Version: 2.1
Name: example_package_iker8
Version: 0.0.1
Summary: Ejemplo de como crear un paquete
Project-URL: Homepage, https://github.com/ikergabirondo/subir_pypi
Project-URL: Bug Tracker, https://github.com/ikergabirondo/subir_pypi/issues
Author-email: iker8 <ikergabirondo8@gmail.com>
License: Copyright (c) 2018 The Python Packaging Authority
License-File: LICENSE
Classifier: License :: OSI Approved :: MIT License
Classifier: Operating System :: OS Independent
Classifier: Programming Language :: Python :: 3
Requires-Python: >=3.9
